vectorfieldplot.py
vectorfieldplot-1.3.1.dist-info/LICENSE
vectorfieldplot-1.3.1.dist-info/WHEEL
vectorfieldplot-1.3.1.dist-info/METADATA
vectorfieldplot-1.3.1.dist-info/RECORD
