Metadata-Version: 2.1
Name: vectorfieldplot
Version: 1.3.1
Summary: A python module for creating high-quality images of electric field lines.
License: MIT
Author: CD Clark III
Author-email: clifton.clark@gmail.com
Requires-Python: >=3.8,<3.12
Classifier: License :: OSI Approved :: MIT License
Classifier: Programming Language :: Python :: 3
Classifier: Programming Language :: Python :: 3.10
Classifier: Programming Language :: Python :: 3.8
Classifier: Programming Language :: Python :: 3.9
Requires-Dist: lxml (>=4.9.1,<5.0.0)
Requires-Dist: numpy (>=1.23.3,<2.0.0)
Requires-Dist: scipy (>=1.9.1,<2.0.0)
